sequence_transfer/__init__.py
sequence_transfer/contextualized_sequence_transfer.py
sequence_transfer/lcs_transfer.py
sequence_transfer/magic_transfer.py
sequence_transfer/sequence.py
sequence_transfer/sequence_transfer.py
sequence_transfer/token_to_text_transfer.py
sequence_transfer/normalizer/__init__.py
sequence_transfer/normalizer/remove_accents.py
sequence_transfer/normalizer/remove_bert_separator.py
sequence_transfer/normalizer/remove_html_entities.py
sequence_transfer/normalizer/remove_whitespace.py
sequence_transfer/normalizer/replace_entity.py
sequence_transfer/normalizer/to_lower.py
sequence_transfer/plugin/entity_annotation_transfer_plugin.py
sequence_transfer-0.1.0.dist-info/LICENSE.txt
sequence_transfer-0.1.0.dist-info/METADATA
sequence_transfer-0.1.0.dist-info/WHEEL
sequence_transfer-0.1.0.dist-info/top_level.txt
sequence_transfer-0.1.0.dist-info/RECORD
