Metadata-Version: 2.1
Name: sequence-transfer
Version: 0.1.0
Summary: A sequence transfer library for NLP
Home-page: https://github.com/Pangeamt/sequence_transfer
Author: Laurent Bié
Author-email: l.bie@pangeanic.com
License: BSD 2-clause
Platform: UNKNOWN
Classifier: Development Status :: 1 - Planning
Classifier: Intended Audience :: Science/Research
Classifier: License :: OSI Approved :: MIT License
Classifier: Operating System :: POSIX :: Linux
Classifier: Programming Language :: Python :: 3.7
Requires-Dist: colorama
Requires-Dist: PrettyTable
Requires-Dist: pytablewriter
